{
  "UsersTable": [
    {
      "id": 1,
      "email": "braxton.shoop@hotmail.com",
      "address": "1513 Hayden Blvd",
      "registrationDate": "Fri Jan 22 2021 05:50:18 GMT-0600 (Central Standard Time)"
    },
    {
      "email": "braxton.shoop@gmail.com",
      "address": "1513 Hayden Drive",
      "registrationDate": "Sat Jan 23 2021 14:11:29 GMT-0600 (Central Standard Time)",
      "id": 2
    }
  ],
  "Messages": [],
  "Toolstable": [
    {
      "id": 1,
      "userid": 2,
      "lenderId": 2,
      "toolstatus": true,
      "toolpicture": "https://res.cloudinary.com/dstfvbrwf/image/upload/v1611433850/ToolMeOnce/b4egohqljekwyfe9254g.jpg"
    },
    {
      "lenderId": 2,
      "toolstatus": true,
      "toolpicture": "https://res.cloudinary.com/dstfvbrwf/image/upload/v1611434051/ToolMeOnce/vcotckzqmdhhk8nqzjo2.jpg",
      "id": 2
    }
  ]
}